{
  "name":"Thomas Higson",
  "email":"Thomas.Higson@gmail.com",
  "banner":"banner-background.jpg",
  "portrait":"banner-face.png",
  "twitter":"https://twitter.com/TaekHigson",
  "linkedIn":"https://www.linkedin.com/in/tomhigson/",
  "gitHub":"https://github.com/tomhigson",
  "description":"intro.md",
  "fields": [
    "Cloud architecture",
    "Microservice architecture",
    "Web apps and services",
    "DevOps / System Reliability Engineering",
    "Agile development",
    "Model based systems engineering (MBSE)",
    "Systems Modelling Language (SysML)",
    "User experience design",
    "People Management",
    "Mentoring",
    "Delivering training",
    "Aerospace safety analysis using IEC61508",
    "Automotive safety analysis using ISO26262",
    "Modularity and reuse across product lines"
  ],
  "jobs": [
    {
      "id":"Engineering-Manager-at-General-Dynamics",
      "companyName":"General Dynamics",
      "level":"Engineering Manager",
      "logo":"gd.png",
      "link":"https://www.gd.com/",
      "start":"2017-09-01",
      "contact":"Bina Taylor",
      "contactEmail":"bina.taylor@gd-ms.uk",
      "roles": [
        {
          "position":"3rd party developer lead for Evolve to Open",
          "image":"gd2.png",
          "imageAlt": "A slide showing a simplified view of the development environment we are creating",
          "description": "gd2.md"
        },
        {
          "position":"Vertex engineering lead",
          "image":"gd1.png",
          "imageAlt": "Promotional image abstractly showing the Vertex concept",
          "description":"gd1.md"
        }
      ],
      "technologies": [
        {
          "name":"Azure",
          "link":"https://azure.microsoft.com"
        },
        {
          "name":"Office 365",
          "link":"https://www.office.com/"
        },
        {
          "name":"REST & OData",
          "link":"https://www.odata.org/"
        },
        {
          "name":"Swagger",
          "link":"https://swagger.io/"
        },
        {
          "name":"Progressive Web Apps",
          "link":"https://developers.google.com/web/progressive-web-apps/"
        },
        {
          "name":"Powershell",
          "link":"https://docs.microsoft.com/en-us/powershell/scripting"
        },
        {
          "name":"Git",
          "link":"https://git-scm.com/"
        },
        {
          "name":"Rational Rhapsody",
          "link":"https://www.ibm.com/uk-en/marketplace/rational-rhapsody"
        },
        {
          "name":"Rational DOORS",
          "link":"https://www.ibm.com/us-en/marketplace/rational-doors"
        },
        {
          "name":"Rational Team Concert",
          "link":"https://www.ibm.com/uk-en/marketplace/change-and-configuration-management"
        }
      ]
    },
    {
      "id":"Personal-Development",
      "level":"Personal Development",
      "logo":"personal.png",
      "roles": [
        {
          "position":"Developer of CV App",
          "description": "personal1.md"
        },
        {
          "position":"Developer of graphical recipe web app",
          "image":"personal1.png",
          "imageAlt":"Early concept of the reciepe system",
          "description": "personal2.md"
        },
        {
          "position":"Other",
          "description": "personal3.md"
        }
      ],
      "technologies": [
        {
          "name":"Azure",
          "link":"https://azure.microsoft.com"
        },
        {
          "name":"Angular",
          "link":"https://angular.io/"
        },
        {
          "name":"Progressive Web Apps",
          "link":"https://developers.google.com/web/progressive-web-apps/"
        },
        {
          "name":"JavaScript / TypeScript",
          "link":"https://www.javascript.com/"
        },
        {
          "name":"NPM",
          "link":"https://www.npmjs.com/"
        },
        {
          "name":"D3.js",
          "link":"https://d3js.org/"
        },
        {
          "name":"HTML",
          "link":"https://en.wikipedia.org/wiki/HTML"
        },
        {
          "name":"CSS / SASS",
          "link":"https://sass-lang.com/"
        },
        {
          "name":"Powershell",
          "link":"https://docs.microsoft.com/en-us/powershell/scripting"
        },
        {
          "name":"Git",
          "link":"https://git-scm.com/"
        },
        {
          "name":"Markdown",
          "link":"https://daringfireball.net/projects/markdown/syntax"
        },
        {
          "name":"Adobe Photoshop",
          "link":"https://www.adobe.com/uk/creativecloud"
        },
        {
          "name":"Adobe Premier Pro",
          "link":"https://www.adobe.com/uk/creativecloud"
        }
      ]
    },
    {
      "id":"Engineering-Manager-at-ZF-TRW",
      "companyName":"ZF TRW",
      "level":"Engineering Manager",
      "logo":"zf.png",
      "link":"https://www.zf.com",
      "start":"2016-09-01",
      "end":"2017-09-01",
      "roles": [
        {
          "position":"System safety lead for radar customer projects",
          "image":"zf1.png",
          "imageAlt":"Advertising render of the adaptive cruise control function",
          "description": "zf1.md"
        }
      ],
      "technologies": [
        {
          "name":"IQ-RM Pro",
          "link":"https://www.apis-iq.com/software/products/apis-iq-rm-pro/"
        },
        {
          "name":"FaultTree +",
          "link":"https://www.isograph.com/software/reliability-workbench/fault-tree-analysis-software/"
        },
        {
          "name":"Rational Rhapsody",
          "link":"https://www.ibm.com/uk-en/marketplace/rational-rhapsody"
        },
        {
          "name":"Rational DOORS",
          "link":"https://www.ibm.com/us-en/marketplace/rational-doors"
        }
      ]
    },
    {
      "id":"Principal-Manager-at-MBDA-Systems",
      "companyName":"MBDA Systems",
      "level":"Principal Engineer",
      "logo":"mbda.png",
      "link":"https://www.mbda-systems.com/",
      "start":"2009-06-01",
      "end":"2016-09-01",
      "roles": [
        {
          "position":"System architect for Future Cruise & Anti-Ship System",
          "image":"mbda1.png",
          "imageAlt":"A concept visions rendering of the system",
          "description": "mbda1.md"
        },
        {
          "position":"Flight path management domain lead for Fire Shadow",
          "image":"mbda2.png",
          "imageAlt":"A successful trial of the system",
          "description": "mbda2.md"
        },
        {
          "position":"Company Improvement",
          "description": "mbda3.md"
        }
      ],
      "technologies": [
        {
          "name":"Java",
          "link":"https://www.java.com/en/"
        },
        {
          "name":"Rational Rhapsody",
          "link":"https://www.ibm.com/uk-en/marketplace/rational-rhapsody"
        },
        {
          "name":"Rational DOORS",
          "link":"https://www.ibm.com/us-en/marketplace/rational-doors"
        },
        {
          "name":"Rational Team Concert",
          "link":"https://www.ibm.com/uk-en/marketplace/change-and-configuration-management"
        }
      ]
    },
    {
      "id":"Graduate-Engineer-at-Thales",
      "companyName":"Thales",
      "level":"Graduate Engineer",
      "logo":"thales.png",
      "link":"http://www.thalesgroup.com/en",
      "start":"2007-09-01",
      "end":"2009-06-01",
      "roles": [
        {
          "position":"Software engineer for covert radio system",
          "image":"thales2.png",
          "imageAlt":"A radio similar to the one developed",
          "description": "thales1.md"
        },
        {
          "position":"Software engineer for Command & Control Information System",
          "description": "thales2.md"
        },
        {
          "position":"Research engineer for military tracking system",
          "image":"thales1.png",
          "imageAlt":"The tracking system ruggedises and repurposes commercial off-the-shelf technology",
          "description": "thales3.md"
        }
      ],
      "technologies": [
        {
          "name":"C#",
          "link":"https://docs.microsoft.com/en-us/dotnet/csharp/"
        },
        {
          "name":"C++",
          "link":"http://www.cplusplus.com/"
        },
        {
          "name":"SQL",
          "link":"https://en.wikipedia.org/wiki/SQL"
        },
        {
          "name":"Windows Server",
          "link":"https://en.wikipedia.org/wiki/Windows_Server"
        },
        {
          "name":"Oracle Database",
          "link":"https://www.oracle.com/uk/database/"
        }
      ]
    },
    {
      "id":"University",
      "companyName":"The University Of Manchester",
      "level":"B.Sc. in Computer Science",
      "logo":"uni.png",
      "link":"http://www.manchester.ac.uk/",
      "start":"2004-09-01",
      "end":"2007-09-01",
      "description":"uni1.md"
    },
    {
      "id":"IT-Admin-at-Wren-Utilities",
      "companyName":"Wren Utilities",
      "level":"IT Administrator",
      "logo":"wren.png",
      "start":"2003-08-01",
      "end":"2004-09-01",
      "description":"wren1.md"
    },
    {
      "id":"College",
      "companyName":"Holy Cross College",
      "level":"Advanced Level Qualification",
      "logo":"college.png",
      "link":"https://www.holycross.ac.uk/",
      "start":"2001-08-01",
      "end":"2003-08-01",
      "description":"college1.md"
    }
  ]
}